{
    "appid": "wxcd487cd2a1eb8889",
    "compileType": "miniprogram",
    "libVersion": "2.26.1",
    "packOptions": {
        "ignore": [],
        "include": []
    },
    "setting": {
        "coverView": true,
        "es6": true,
        "postcss": true,
        "minified": true,
        "enhance": true,
        "showShadowRootInWxmlPanel": true,
        "packNpmRelationList": [],
        "babelSetting": {
            "ignore": [],
            "disablePlugins": [],
            "outputPath": ""
        },
        "minifyWXML": true,
        "minifyWXSS": true
    },
    "condition": {},
    "editorSetting": {
        "tabIndent": "auto",
        "tabSize": 4
    },
    "simulatorPluginLibVersion": {}
}